post_ext_web/__init__.py
post_ext_web/_version.py
post_ext_web-0.1.0.data/data/share/jupyter/labextensions/post_ext_web/build_log.json
post_ext_web-0.1.0.data/data/share/jupyter/labextensions/post_ext_web/package.json
post_ext_web-0.1.0.data/data/share/jupyter/labextensions/post_ext_web/static/lib_index_js.241f57061c601f22ea56.js
post_ext_web-0.1.0.data/data/share/jupyter/labextensions/post_ext_web/static/lib_index_js.241f57061c601f22ea56.js.map
post_ext_web-0.1.0.data/data/share/jupyter/labextensions/post_ext_web/static/remoteEntry.5d3977da46df592f6859.js
post_ext_web-0.1.0.data/data/share/jupyter/labextensions/post_ext_web/static/remoteEntry.5d3977da46df592f6859.js.map
post_ext_web-0.1.0.data/data/share/jupyter/labextensions/post_ext_web/static/style.js
post_ext_web-0.1.0.data/data/share/jupyter/labextensions/post_ext_web/static/style_index_js.6df1b64b84a0c3c02a9e.js
post_ext_web-0.1.0.data/data/share/jupyter/labextensions/post_ext_web/static/style_index_js.6df1b64b84a0c3c02a9e.js.map
post_ext_web-0.1.0.data/data/share/jupyter/labextensions/post_ext_web/install.json
post_ext_web-0.1.0.dist-info/METADATA
post_ext_web-0.1.0.dist-info/WHEEL
post_ext_web-0.1.0.dist-info/licenses/LICENSE
post_ext_web-0.1.0.dist-info/RECORD
